Workbook

Sheet 01_Productos
A1: ID_Producto | B1: Nombre_Producto | C1: Categoria | D1: Stock_Inicial | E1: Precio_Unitario | F1: Costo_Unitario | G1: Reabastecer | H1: Total_vendido | I1: Stock_Actual
A2: PROD-001 | B2: Monitor 24" | C2: Electrónica | D2: 50 | E2: 180 | F2: 110 | G2: =IF(I2<=25, "⚠️ REABASTECER", "OK") -> OK | H2: =SUMIF('02_Ventas'!C:C, A2, '02_Ventas'!D:D) -> 6 | I2: =D2-H2 -> 44
A3: PROD-002 | B3: Teclado Mecánico | C3: Electrónica | D3: 120 | E3: 65 | F3: 35 | G3: =IF(I3<=25, "⚠️ REABASTECER", "OK") -> OK | H3: =SUMIF('02_Ventas'!C:C, A3, '02_Ventas'!D:D) -> 5 | I3: =D3-H3 -> 115
A4: PROD-003 | B4: Silla Ergonomica | C4: Mobiliario | D4: 30 | E4: 210 | F4: 120 | G4: =IF(I4<=25, "⚠️ REABASTECER", "OK") -> OK | H4: =SUMIF('02_Ventas'!C:C, A4, '02_Ventas'!D:D) -> 3 | I4: =D4-H4 -> 27
A5: PROD-004 | B5: Ratón Inalámbrico | C5: Electrónica | D5: 200 | E5: 25 | F5: 10 | G5: =IF(I5<=25, "⚠️ REABASTECER", "OK") -> OK | H5: =SUMIF('02_Ventas'!C:C, A5, '02_Ventas'!D:D) -> 15 | I5: =D5-H5 -> 185
A6: PROD-005 | B6: Escritorio Madera | C6: Mobiliario | D6: 15 | E6: 350 | F6: 200 | G6: =IF(I6<=25, "⚠️ REABASTECER", "OK") -> ⚠️ REABASTECER | H6: =SUMIF('02_Ventas'!C:C, A6, '02_Ventas'!D:D) -> 2 | I6: =D6-H6 -> 13
A7: PROD-006 | B7: Auriculares BT | C7: Electrónica | D7: 80 | E7: 85 | F7: 45 | G7: =IF(I7<=25, "⚠️ REABASTECER", "OK") -> OK | H7: =SUMIF('02_Ventas'!C:C, A7, '02_Ventas'!D:D) -> 4 | I7: =D7-H7 -> 76
A8: PROD-007 | B8: Lámpara LED | C8: Iluminación | D8: 100 | E8: 30 | F8: 12 | G8: =IF(I8<=25, "⚠️ REABASTECER", "OK") -> OK | H8: =SUMIF('02_Ventas'!C:C, A8, '02_Ventas'!D:D) -> 8 | I8: =D8-H8 -> 92

Sheet 02_Ventas
A1: ID_Venta | B1: Fecha | C1: ID_Producto | D1: Cantidad_Vendida | E1: Categoria | F1: Precio_Unitario | G1: Ingreso_Total
A2: VEN-1001 | B2: 46082 | C2: PROD-001 | D2: 2 | E2: =VLOOKUP(C2, '01_Productos'!A:C, 3, FALSE) -> Electrónica | F2: =VLOOKUP(C2, '01_Productos'!A:E, 5, FALSE) -> 180 | G2: =D2*F2 -> 360
A3: VEN-1002 | B3: 46082 | C3: PROD-004 | D3: 5 | E3: =VLOOKUP(C3, '01_Productos'!A:C, 3, FALSE) -> Electrónica | F3: =VLOOKUP(C3, '01_Productos'!A:E, 5, FALSE) -> 25 | G3: =D3*F3 -> 125
A4: VEN-1003 | B4: 46083 | C4: PROD-002 | D4: 3 | E4: =VLOOKUP(C4, '01_Productos'!A:C, 3, FALSE) -> Electrónica | F4: =VLOOKUP(C4, '01_Productos'!A:E, 5, FALSE) -> 65 | G4: =D4*F4 -> 195
A5: VEN-1004 | B5: 46083 | C5: PROD-003 | D5: 1 | E5: =VLOOKUP(C5, '01_Productos'!A:C, 3, FALSE) -> Mobiliario | F5: =VLOOKUP(C5, '01_Productos'!A:E, 5, FALSE) -> 210 | G5: =D5*F5 -> 210
A6: VEN-1005 | B6: 46084 | C6: PROD-001 | D6: 1 | E6: =VLOOKUP(C6, '01_Productos'!A:C, 3, FALSE) -> Electrónica | F6: =VLOOKUP(C6, '01_Productos'!A:E, 5, FALSE) -> 180 | G6: =D6*F6 -> 180
A7: VEN-1006 | B7: 46084 | C7: PROD-005 | D7: 2 | E7: =VLOOKUP(C7, '01_Productos'!A:C, 3, FALSE) -> Mobiliario | F7: =VLOOKUP(C7, '01_Productos'!A:E, 5, FALSE) -> 350 | G7: =D7*F7 -> 700
A8: VEN-1007 | B8: 46085 | C8: PROD-004 | D8: 10 | E8: =VLOOKUP(C8, '01_Productos'!A:C, 3, FALSE) -> Electrónica | F8: =VLOOKUP(C8, '01_Productos'!A:E, 5, FALSE) -> 25 | G8: =D8*F8 -> 250
A9: VEN-1008 | B9: 46085 | C9: PROD-006 | D9: 4 | E9: =VLOOKUP(C9, '01_Productos'!A:C, 3, FALSE) -> Electrónica | F9: =VLOOKUP(C9, '01_Productos'!A:E, 5, FALSE) -> 85 | G9: =D9*F9 -> 340
A10: VEN-1009 | B10: 46086 | C10: PROD-002 | D10: 2 | E10: =VLOOKUP(C10, '01_Productos'!A:C, 3, FALSE) -> Electrónica | F10: =VLOOKUP(C10, '01_Productos'!A:E, 5, FALSE) -> 65 | G10: =D10*F10 -> 130
A11: VEN-1010 | B11: 46086 | C11: PROD-007 | D11: 8 | E11: =VLOOKUP(C11, '01_Productos'!A:C, 3, FALSE) -> Iluminación | F11: =VLOOKUP(C11, '01_Productos'!A:E, 5, FALSE) -> 30 | G11: =D11*F11 -> 240
A12: VEN-1011 | B12: 46087 | C12: PROD-001 | D12: 3 | E12: =VLOOKUP(C12, '01_Productos'!A:C, 3, FALSE) -> Electrónica | F12: =VLOOKUP(C12, '01_Productos'!A:E, 5, FALSE) -> 180 | G12: =D12*F12 -> 540
A13: VEN-1012 | B13: 46087 | C13: PROD-003 | D13: 2 | E13: =VLOOKUP(C13, '01_Productos'!A:C, 3, FALSE) -> Mobiliario | F13: =VLOOKUP(C13, '01_Productos'!A:E, 5, FALSE) -> 210 | G13: =D13*F13 -> 420

Sheet 03_Dashboard
A1: Total de Productos Distintos | B1: =COUNTA('01_Productos'!A2:A8) -> 7
A2: Productos a Rebastecer | B2: =COUNTIF('01_Productos'!G2:G8, "⚠️ REABASTECER") -> 1
A3: Total de de Unidades Vendidas | B3: =SUM('02_Ventas'!D2:D13) -> 43
